RMK_support/IO_support.py
RMK_support/__init__.py
RMK_support/amjuel_reader.py
RMK_support/amjuel_support.py
RMK_support/calculation_tree_support.py
RMK_support/common_models.py
RMK_support/common_variables.py
RMK_support/crm_support.py
RMK_support/dashboard_support.py
RMK_support/derivations.py
RMK_support/grid.py
RMK_support/integrators.py
RMK_support/model_construction.py
RMK_support/remkit_context.py
RMK_support/sk_normalization.py
RMK_support/stencils.py
RMK_support/tex_parsing.py
RMK_support/variable_container.py
rmk_support-2.0.0.dist-info/licenses/LICENSE.md
rmk_support-2.0.0.dist-info/METADATA
rmk_support-2.0.0.dist-info/WHEEL
rmk_support-2.0.0.dist-info/top_level.txt
rmk_support-2.0.0.dist-info/RECORD
