Metadata-Version: 2.4
Name: RMK_support
Version: 2.0.0
Summary: Python modules and notebooks used to initialize and analyze ReMKiT1D runs
Author: UK Atomic Energy Authority
Maintainer: Stefan Mijin
Maintainer-email: Stefan Mijin <stefan.mijin@ukaea.uk>
License: GPLv3
Requires-Python: >=3.8
License-File: LICENSE.md
Requires-Dist: numpy
Requires-Dist: xarray
Requires-Dist: holoviews
Requires-Dist: panel
Requires-Dist: matplotlib
Requires-Dist: h5py
Requires-Dist: scipy
Requires-Dist: pylatex
Dynamic: license-file
Dynamic: maintainer
